MANIFEST.in
README.rst
setup.py
Steno.egg-info/PKG-INFO
Steno.egg-info/SOURCES.txt
Steno.egg-info/dependency_links.txt
Steno.egg-info/entry_points.txt
Steno.egg-info/requires.txt
Steno.egg-info/top_level.txt
steno/__init__.py
steno/defaults.py
steno/dialogs.py
steno/droptargets.py
steno/events.py
steno/ids.py
steno/player.py
steno/player_content.py
steno/player_gui.py
steno/player_settings.py
steno/steno.py
steno/translator.py
steno/verificator.py
steno/widgets.py
steno/resources/html/user_manual.html
steno/resources/img/help.png
steno/resources/img/icon_128x128.png
steno/resources/img/icon_16x16.png
steno/resources/img/icon_32x32.png
steno/resources/img/icon_48x48.png
steno/resources/img/icon_64x64.png
steno/resources/img/pause.png
steno/resources/img/play.png
steno/resources/img/repeat.png
steno/resources/img/stop.png
steno/test/__init__.py
steno/test/test_verificator.py
steno/test/test_widgets.py