Metadata-Version: 1.1
Name: Steno
Version: 0.1b3
Summary: An application that helps people learning a foreign language to train listening skills.
Home-page: https://github.com/antonkonyshev/steno/
Author: Anton Konyshev
Author-email: anton.konyshev@gmail.com
License: wxWidgets Library License (LGPL derivative)
Keywords: language listening trainer learning education
Platform: UNKNOWN
Classifier: Development Status :: 4 - Beta
Classifier: Environment :: Win32 (MS Windows)
Classifier: Environment :: X11 Applications :: GTK
Classifier: Intended Audience :: Education
Classifier: Intended Audience :: End Users/Desktop
Classifier: License :: OSI Approved
Classifier: Operating System :: Microsoft :: Windows
Classifier: Operating System :: POSIX :: Linux
Classifier: Programming Language :: Python
Classifier: Topic :: Education
Classifier: Topic :: Multimedia :: Video :: Display
